[
  {
    "id": 1,
    "name": "Grill 5",
    "restaurantType": "barbecue",
    "isOpen": true,
    "logo": "../assets/images/logos/restaurant-logos/grill5.png",
    "bannerImage": "../assets/images/restaurant-images/banners/grill5.jpg",
    "coverImage": "../assets/images/restaurant-images/covers/grill5.jpg",
    "rating": 5.0,
    "location": {
      "longitude": "414114",
      "latitude": "444324",
      "address": {
        "street": "Maksima Gorkog",
        "number": "55",
        "city": {
          "name": "Novi Sad",
          "postalCode": "21000"
        }
      }
    },
    "articles": [
      {
      	"restaurantId": 1,
        "name": "Steak",
        "price": 12.39,
        "articleType": "meal",
        "quantity": 81,
        "description": "A good steak is juicy, tender, loaded with flavor, and has a minimum amount of fat.",
        "image": "../assets/images/restaurant-images/foods/001.jpg"
      },
      {
        "restaurantId": 1,
        "name": "Hamburger",
        "price": 7.39,
        "articleType": "meal",
        "quantity": 40,
        "description": "Juicy, big, loaded with toppings of your choice.",
        "image": "../assets/images/restaurant-images/foods/002.jpg"
      },
      {
        "restaurantId": 1,
        "name": "Kebabs",
        "price": 9.79,
        "articleType": "meal",
        "quantity": 64,
        "description": "Fresh kekabs with onion and delicious graviola! Try it with spicy sauce for better taste.",
        "image": "../assets/images/restaurant-images/foods/003.jpg"
      },
      {
        "restaurantId": 1,
        "name": "Capricciosa",
        "price": 6.99,
        "articleType": "meal",
        "quantity": 120,
        "description": "Dish of Italian origin, topped with some combination of olive oil, oregano and tomato.",
        "image": "../assets/images/restaurant-images/foods/004.jpg"
      },
      {
        "restaurantId": 1,
        "name": "Beef ",
        "price": 11.39,
        "articleType": "meal",
        "quantity": 34,
        "description": "Asian-inspired flavors with a French technique give this dish its own unique spin.",
        "image": "../assets/images/restaurant-images/foods/005.jpg"
      },
      {
        "restaurantId": 1,
        "name": "Burger",
        "price": 6.49,
        "articleType": "meal",
        "quantity": 133,
        "description": "Tasty, delicious, and will have you craving more on the first bite.",
        "image": "../assets/images/restaurant-images/foods/006.jpg"
      },
      {
        "restaurantId": 1,
        "name": "Lemonade",
        "price": 2.49,
        "articleType": "drink",
        "quantity": 100,
        "description": "A beverage of sweetened lemon juice mixed with water.",
        "image": "../assets/images/restaurant-images/foods/011.jpg"
      },
      {
        "restaurantId": 1,
        "name": "Strawberry juice",
        "price": 4.49,
        "articleType": "drink",
        "quantity": 85,
        "description": "Strawberries shine in this tall, refreshing, gingery cocktail.",
        "image": "../assets/images/restaurant-images/foods/012.jpg"
      },
      {
        "restaurantId": 1,
        "name": "Coca Cola",
        "price": 1.99,
        "articleType": "drink",
        "quantity": 76,
        "description": "Fresh, cold and sweet drink.",
        "image": "../assets/images/restaurant-images/foods/013.jpg"
      },
      {
        "restaurantId": 1,
        "name": "Orange juice",
        "price": 3.49,
        "articleType": "drink",
        "quantity": 93,
        "description": "100% pure-squeezed, pasteurized orange juice.",
        "image": "../assets/images/restaurant-images/foods/014.jpg"
      }
    ],
    "isDeleted": false
  },
  {
    "id": 2,
    "name": "Los Pollos Hermanos",
    "restaurantType": "barbecue",
    "isOpen": true,
    "logo": "../assets/images/logos/restaurant-logos/los-pollos-hermanos.png",
    "bannerImage": "../assets/images/restaurant-images/banners/los-pollos-hermanos.jpg",
    "coverImage": "../assets/images/restaurant-images/covers/los-pollos-hermanos.jpg",
    "rating": 4.0,
    "location": {
      "longitude": "111333",
      "latitude": "412111",
      "address": {
        "street": "Niksicka",
        "number": "46A",
        "city": {
          "name": "Belgrade",
          "postalCode": "181000"
        }
      }
    },
    "articles": [],
    "isDeleted": false
  },
  {
    "id": 3,
    "name": "Dine Fine",
    "restaurantType": "italian",
    "isOpen": true,
    "logo": "../assets/images/logos/restaurant-logos/dine-fine.png",
    "bannerImage": "../assets/images/restaurant-images/banners/dine-fine.jpg",
    "coverImage": "../assets/images/restaurant-images/covers/dine-fine.jpg",
    "rating": 3.0,
    "location": {
      "longitude": "113213",
      "latitude": "433311",
      "address": {
        "street": "Skerliceva",
        "number": "17",
        "city": {
          "name": "Kragujevac",
          "postalCode": "34000"
        }
      }
    },
    "articles": [],
    "isDeleted": false
  },
  {
    "id": 4,
    "name": "The Bacon Diet",
    "restaurantType": "barbecue",
    "isOpen": false,
    "logo": "../assets/images/logos/restaurant-logos/the-bacon-diet.png",
    "bannerImage": "../assets/images/restaurant-images/banners/the-bacon-diet.jpg",
    "coverImage": "../assets/images/restaurant-images/covers/the-bacon-diet.jpg",
    "rating": 0.0,
    "location": {
      "longitude": "166623",
      "latitude": "415321",
      "address": {
        "street": "Bulevar Oslobodjenja",
        "number": "65B",
        "city": {
          "name": "Novi Sad",
          "postalCode": "21000"
        }
      }
    },
    "articles": [],
    "isDeleted": false
  },
  {
    "id": 5,
    "name": "McDonalds",
    "restaurantType": "barbecue",
    "isOpen": true,
    "logo": "../assets/images/logos/restaurant-logos/mcdonalds.png",
    "bannerImage": "../assets/images/restaurant-images/banners/mcdonalds.jpg",
    "coverImage": "../assets/images/restaurant-images/covers/mcdonalds.jpg",
    "rating": 0.0,
    "location": {
      "longitude": "166113",
      "latitude": "433321",
      "address": {
        "street": "Laze Kostica",
        "number": "2",
        "city": {
          "name": "Novi Sad",
          "postalCode": "21000"
        }
      }
    },
    "articles": [],
    "isDeleted": false
  },
  {
    "id": 6,
    "name": "Burger King",
    "restaurantType": "barbecue",
    "isOpen": true,
    "logo": "../assets/images/logos/restaurant-logos/burger-king.png",
    "bannerImage": "../assets/images/restaurant-images/banners/burger-king.jpg",
    "coverImage": "../assets/images/restaurant-images/covers/burger-king.jpg",
    "rating": 0.0,
    "location": {
      "longitude": "444156",
      "latitude": "515322",
      "address": {
        "street": "Knez Mihajlova",
        "number": "33A",
        "city": {
          "name": "Belgrade",
          "postalCode": "113000"
        }
      }
    },
    "articles": [],
    "isDeleted": false
  }
]
